app/__init__.py
app/context.py
app/main.py
app/base/__init__.py
app/base/abstract.py
app/models/__init__.py
app/models/path_models.py
app/models/settings_model.py
app/repositories/__init__.py
app/repositories/json_repositories.py
app/repositories/json_dir/last_template.json
app/repositories/json_dir/saved_templates.json
app/routers/__init__.py
app/routers/view.py
app/services/__init__.py
app/services/from_alias.py
app/services/from_last.py
app/services/from_path.py
app/utils/__init__.py
app/utils/models_utils.py
app/utils/path_utils.py
app/visualize/__init__.py
app/visualize/facade.py
app/visualize/readers.py
app/visualize/visualizers.py
tmp_box-0.1.0.dist-info/METADATA
tmp_box-0.1.0.dist-info/WHEEL
tmp_box-0.1.0.dist-info/entry_points.txt
tmp_box-0.1.0.dist-info/top_level.txt
tmp_box-0.1.0.dist-info/RECORD
