Metadata-Version: 2.1
Name: tmp_box
Version: 0.1.0
Requires-Dist: typer >=0.12.3
Requires-Dist: pydantic >=2.7.2
